tftracer/__init__.py
tftracer/__main__.py
tftracer/monkey_patching.py
tftracer/timeline.py
tftracer/timeline_visualizer.py
tftracer/tracing_server.py
tftracer/version.py
tftracer/resources/templates/on_change_callback.js
tftracer/resources/templates/on_click_callback.js
tftracer/resources/templates/on_hover_callback.js
tftracer/resources/templates/timeline.html
tftracer/resources/templates/tooltips.html
tftracer/resources/templates/update_ranges.js
tftracer/resources/web/app.js
tftracer/resources/web/main.html
tftracer/resources/web/tensorflow.png
tensorflow_tracer-1.1.0.dist-info/LICENSE
tensorflow_tracer-1.1.0.dist-info/METADATA
tensorflow_tracer-1.1.0.dist-info/WHEEL
tensorflow_tracer-1.1.0.dist-info/entry_points.txt
tensorflow_tracer-1.1.0.dist-info/top_level.txt
tensorflow_tracer-1.1.0.dist-info/RECORD
