Metadata-Version: 2.1
Name: tensorflow-tracer
Version: 1.1.0
Summary: Runtime Tracing Library for TensorFlow
Home-page: https://github.com/xldrx/tensorflow-tracer
Author: Sayed Hadi Hashemi
Author-email: SayedHadiHashemi@gmail.com
License: Apache-2.0
Platform: UNKNOWN
Classifier: Programming Language :: Python :: 3 :: Only
Classifier: Development Status :: 4 - Beta
Classifier: License :: OSI Approved :: Apache Software License
Classifier: Operating System :: OS Independent
Requires-Dist: bokeh (>=1.0)
Requires-Dist: flask
Requires-Dist: jinja2
Requires-Dist: tensorflow (>=1.8)
Requires-Dist: six
Requires-Dist: gevent
